6th Class/stopwatch.v
module stopwatch 
(
    input wire clk,
    input wire reset,
    output wire [3:0] d,
    output wire max_tick
);

//T = 20ns 
//f = 1/T = 50 x 10^6 Hz
//1s -> 50 x 10^6 pulse
// 50 x 10^6 pulse -> 1s
// 1 pulse -> 1s / (50 x 10^6)
// 5 x 10^6 pulse -> 0.1s
// Register size = log2(5x10^6) = 22.25 => 23 bits
// Save 9 value in register = 4 bits
// 1s second a tick generate korbe means output 1 hobe

// localparam DVSR = 5000000;
localparam DVSR = 2;

wire [22:0] ms_next;
reg [22:0] ms_reg;

wire [3:0] second_counter_next;
reg [3:0] second_counter_reg;


//memory/register/d_ff
always @(posedge clk, posedge reset) 
begin
    if (reset)
    begin
        ms_reg <= 23'b0000_0000_0000_0000_0000_000;
        second_counter_reg <= 4'b0000;        
    end
    else
    begin
        ms_reg <= ms_next;   
        second_counter_reg <= second_counter_next;        
    end
end

//nex state logic
assign ms_next = ms_reg + 1;
assign second_counter_next = (ms_reg==DVSR) ? second_counter_reg + 1 : second_counter_reg;

//output logic
assign d = second_counter_reg;
assign max_tick = (second_counter_reg==4'b1010) ? 1'b1 : 1'b0;

    
endmodule

6th Class/stopwatch_tb.v
`timescale 1ns/1ns

module stopwatch_tb;
    reg clk;
    reg reset;

    wire [3:0] d;
    wire max_tick;  

stopwatch circuit1 (clk, reset, d, max_tick);

always begin
    clk = ~clk;
    #10;
end

initial begin
   $dumpfile("test.vcd");
   $dumpvars(0, stopwatch_tb);

    clk <= 0;
    reset <= 1;
    #20;

    reset <= 0;
    #20;
    #20;
    #20;

    #20;
    #20;

    #20;
    #20;

    #20;
    #20;

    #20;
    #20;

    #20;
    #20;

    $finish;
end

initial begin
    $monitor("clk = %b, reset = %b, d = %b max_tick = %b", clk, reset, d, max_tick);
end


endmodule

6th Class/test.vcd
$date
	Tue Jun 01 21:54:21 2021
$end
$version
	Icarus Verilog
$end
$timescale
	1ns
$end
$scope module stopwatch_tb $end
$var wire 1 ! max_tick $end
$var wire 4 " d [3:0] $end
$var reg 1 # clk $end
$var reg 1 $ reset $end
$scope module circuit1 $end
$var wire 1 # clk $end
$var wire 4 % d [3:0] $end
$var wire 1 $ reset $end
$var wire 4 & second_counter_next [3:0] $end
$var wire 23 ' ms_next [22:0] $end
$var wire 1 ! max_tick $end
$var reg 23 ( ms_reg [22:0] $end
$var reg 4 ) second_counter_reg [3:0] $end
$upscope $end
$upscope $end
$enddefinitions $end
#0
$dumpvars
b0 )
b0 (
b1 '
b0 &
b0 %
1$
0#
b0 "
0!
$end
#10
1#
#20
0$
0#
#30
b10 '
b1 (
1#
#40
0#
#50
b1 &
b11 '
b10 (
1#
#60
0#
#70
b1 "
b1 %
b1 )
b100 '
b11 (
1#
#80
0#
#90
b101 '
b100 (
1#
#100
0#
#110
b110 '
b101 (
1#
#120
0#
#130
b111 '
b110 (
1#
#140
0#
#150
b1000 '
b111 (
1#
#160
0#
#170
b1001 '
b1000 (
1#
#180
0#
#190
b1010 '
b1001 (
1#
#200
0#
#210
b1011 '
b1010 (
1#
#220
0#
#230
b1100 '
b1011 (
1#
#240
0#
#250
b1101 '
b1100 (
1#
#260
0#
#270
b1110 '
b1101 (
1#
