BS_Full/ROM.v
module ROM 
#(
    parameter ADDR_WIDTH = 12,
              DATA_WIDTH = 8
)
(
    input wire [ADDR_WIDTH-1:0] read_addr,
    output reg [DATA_WIDTH-1:0] read_data
);

always @(*) 
begin
    case(read_addr)
        12'h000: read_data = 'b0000_0011;
        12'h001: read_data = 'b0000_0010;
        12'h002: read_data = 'b0000_0001;
        12'h003: read_data = 'b0000_0000;
        12'h004: read_data = 'd4;
        12'h006: read_data = 'd5;
        default: read_data = 'd255;   
    endcase 
end


endmodule

BS_Full/dualPortRAM.v
module dualPortRAM 
#(
    parameter ADDR_WIDTH = 12,
              DATA_WIDTH = 8
)
(
    input wire clk,
    input wire we,
    input wire [ADDR_WIDTH-1:0] read_addr_1,
    input wire [ADDR_WIDTH-1:0] read_addr_2,
    input wire [ADDR_WIDTH-1:0] write_addr,
    input wire [DATA_WIDTH-1:0] write_data,
    output wire [DATA_WIDTH-1:0] read_data_1,
    output wire [DATA_WIDTH-1:0] read_data_2
);

integer idx;
reg [DATA_WIDTH-1:0] ram [2**ADDR_WIDTH-1:0];

initial begin
    $dumpfile("test.vcd");
    for (idx = 0; idx < 2**ADDR_WIDTH; idx = idx + 1) $dumpvars(0, ram[idx]);
end

always @(posedge clk) 
begin
    if(we)
    begin
        ram[write_addr] <= write_data;
        $display("   ==>clk = %b, RAM[0] = %d, RAM[1] = %d, RAM[2] = %d, RAM[3] = %d\n   ==>we=%b, write_addr=%d, write_data=%d\n", clk, ram[0], ram[1], ram[2], ram[3], we, write_addr, write_data);
    end
end

assign read_data_1 = ram[read_addr_1];
assign read_data_2 = ram[read_addr_2];

endmodule

11th Class/BS.v
module BS 
#(
    parameter ADDR_WIDTH = 2,
              DATA_WIDTH = 8          
) 
(
    input wire clk,
    input wire reset,
    input wire start,
    output reg finish
);

parameter SIZE = 2**ADDR_WIDTH;

localparam [3:0] Idle    = 4'b0000,
                 ROM2RAM = 4'b0001,
                 Done    = 4'b0010,
                 Error   = 4'b0011;

reg [3:0] state_reg, state_next;
reg [ADDR_WIDTH:0] addr_reg, addr_next;

//Component Instatiation
wire RAM_we;
wire [ADDR_WIDTH-1:0] RAM_read_addr_1, RAM_read_addr_2, RAM_write_addr;
wire [DATA_WIDTH-1:0] RAM_read_data_1, RAM_read_data_2, RAM_write_data;

dualPortRAM #(.ADDR_WIDTH(2), .DATA_WIDTH(8)) 
RAMcircuit
(
    .clk(clk),
    .we(RAM_we),
    .read_addr_1(RAM_read_addr_1),
    .read_addr_2(RAM_read_addr_2),
    .write_addr(RAM_write_addr),
    .write_data(RAM_write_data),
    .read_data_1(RAM_read_data_1),
    .read_data_2(RAM_read_data_2)
);

wire [ADDR_WIDTH-1:0] ROM_read_addr;
wire [DATA_WIDTH-1:0] ROM_read_data;
ROM #(.ADDR_WIDTH(2), .DATA_WIDTH(8)) 
ROMcircuit
(
    .read_addr(ROM_read_addr),
    .read_data(ROM_read_data)    
);

//Memory
always @(posedge clk, posedge reset) 
begin
    if(reset)
        begin
            state_reg <= Idle;
            addr_reg <= 0;
        end
    else
        begin
            state_reg <= state_next;
            addr_reg <= addr_next;
        end
end


//FSM
always@(*)
begin
    if(state_reg==Idle)
        $monitor("state_reg = IDLE, clk = %b, reset = %b, start = %b, finish = %b\n", clk, reset, start, finish);
    else if(state_reg==ROM2RAM)
        $monitor("state_reg = ROM2RAM, clk = %b, reset = %b, start = %b, finish = %b\n", clk, reset, start, finish);
    else if(state_reg==Done)
        $monitor("state_reg = Done, clk = %b, reset = %b, start = %b, finish = %b\n", clk, reset, start, finish);
    else if(state_reg==Error)
        $monitor("state_reg = Error, clk = %b, reset = %b, start = %b, finish = %b\n", clk, reset, start, finish);

    state_next = state_reg;
    addr_next = addr_reg;
    finish = 1'b0;

    case(state_reg)
        Idle:
            if(start)
            begin
                state_next = ROM2RAM;
                addr_next = 0;
            end
        ROM2RAM:
            begin
                $display("   ==>(ROM2RAM) ==> addr_reg = %d\n", addr_reg);
                if(addr_reg < SIZE)
                begin
                    addr_next = addr_reg + 1;
                end
                else
                begin
                    state_next = Done;
                end
            end
        Done:
            begin
                finish = 1'b1;
                state_next = Idle;
            end
        default: state_next = Error;
    endcase
end

assign RAM_we = (state_reg==ROM2RAM) ? 1 : 0;
assign RAM_read_addr_1 = 0;
assign RAM_read_addr_2 = 0; 
assign RAM_write_addr = (state_reg==ROM2RAM) ? addr_reg : 0;
assign RAM_write_data = (state_reg==ROM2RAM) ? ROM_read_data : 0;

assign ROM_read_addr = (state_reg==ROM2RAM) ? addr_reg : 0;

endmodule

11th Class/BS_tb.v
`timescale 1ns/1ps

module BS_tb 
(
);

reg clk;
reg reset;
reg start;
wire finish;

BS #(.ADDR_WIDTH(2), .DATA_WIDTH(8))
BScircuit
(
.clk(clk),
.reset(reset),
.start(start),
.finish(finish)
);

always begin
    clk = ~clk;
    #10;
end

initial begin
    $dumpfile("test.vcd");
    $dumpvars(0, BS_tb);

    clk <= 0;
    reset <= 1;
    start <= 0;
    #20;

    reset <= 0;
    start <= 1;
    #20;

    start <= 0;

    #1000;

    $finish;
end

// initial begin
//     $monitor("clk = %b, reset = %b, start = %b, finish = %b\n", clk, reset, start, finish);
// end
    
endmodule

11th Class/test.vcd
$date
	Thu Jul 07 21:46:37 2022
$end
$version
	Icarus Verilog
$end
$timescale
	1ps
$end
$scope module BS_tb $end
$scope module BScircuit $end
$scope module RAMcircuit $end
$var reg 8 ! \ram[0] [7:0] $end
$upscope $end
$upscope $end
$upscope $end
$scope module BS_tb $end
$scope module BScircuit $end
$scope module RAMcircuit $end
$var reg 8 " \ram[1] [7:0] $end
$upscope $end
$upscope $end
$upscope $end
$scope module BS_tb $end
$scope module BScircuit $end
$scope module RAMcircuit $end
$var reg 8 # \ram[2] [7:0] $end
$upscope $end
$upscope $end
$upscope $end
$scope module BS_tb $end
$scope module BScircuit $end
$scope module RAMcircuit $end
$var reg 8 $ \ram[3] [7:0] $end
$upscope $end
$upscope $end
$upscope $end
$scope module BS_tb $end
$var wire 1 % finish $end
$var reg 1 & clk $end
$var reg 1 ' reset $end
$var reg 1 ( start $end
$scope module BScircuit $end
$var wire 2 ) RAM_read_addr_1 [1:0] $end
$var wire 2 * RAM_read_addr_2 [1:0] $end
$var wire 1 & clk $end
$var wire 1 ' reset $end
$var wire 1 ( start $end
$var wire 8 + ROM_read_data [7:0] $end
$var wire 2 , ROM_read_addr [1:0] $end
$var wire 8 - RAM_write_data [7:0] $end
$var wire 2 . RAM_write_addr [1:0] $end
$var wire 1 / RAM_we $end
$var wire 8 0 RAM_read_data_2 [7:0] $end
$var wire 8 1 RAM_read_data_1 [7:0] $end
$var parameter 32 2 ADDR_WIDTH $end
$var parameter 32 3 DATA_WIDTH $end
$var parameter 4 4 Done $end
$var parameter 4 5 Error $end
$var parameter 4 6 Idle $end
$var parameter 4 7 ROM2RAM $end
$var parameter 32 8 SIZE $end
$var reg 3 9 addr_next [2:0] $end
$var reg 3 : addr_reg [2:0] $end
$var reg 1 % finish $end
$var reg 4 ; state_next [3:0] $end
$var reg 4 < state_reg [3:0] $end
$scope module RAMcircuit $end
$var wire 1 & clk $end
$var wire 2 = read_addr_1 [1:0] $end
$var wire 2 > read_addr_2 [1:0] $end
$var wire 8 ? read_data_1 [7:0] $end
$var wire 8 @ read_data_2 [7:0] $end
$var wire 1 / we $end
$var wire 2 A write_addr [1:0] $end
$var wire 8 B write_data [7:0] $end
$var parameter 32 C ADDR_WIDTH $end
$var parameter 32 D DATA_WIDTH $end
$var integer 32 E idx [31:0] $end
$upscope $end
$scope module ROMcircuit $end
$var wire 2 F read_addr [1:0] $end
$var parameter 32 G ADDR_WIDTH $end
$var parameter 32 H DATA_WIDTH $end
$var reg 8 I read_data [7:0] $end
$upscope $end
$upscope $end
$upscope $end
$enddefinitions $end
$comment Show the parameter values. $end
$dumpall
b1000 H
b10 G
b1000 D
b10 C
b100 8
b1 7
b0 6
b11 5
b10 4
b1000 3
b10 2
$end
#0
$dumpvars
b11 I
b0 F
b100 E
b0 B
b0 A
bx @
bx ?
b0 >
b0 =
b0 <
b0 ;
b0 :
b0 9
bx 1
bx 0
0/
b0 .
b0 -
b0 ,
b11 +
b0 *
b0 )
0(
1'
0&
0%
bx $
bx #
bx "
bx !
$end
#10000
1&
#20000
b1 ;
1(
0'
0&
#30000
1/
b1 9
b11 -
b11 B
b1 <
b1 ;
1&
#40000
0(
b1 9
0&
#50000
b10 -
b10 B
b10 +
b10 I
b1 .
b1 A
b1 ,
b1 F
b11 !
b11 1
b11 ?
b11 0
b11 @
b1 :
b10 9
1&
#60000
b10 9
0&
#70000
b1 -
b1 B
b1 +
b1 I
b10 .
b10 A
b10 ,
b10 F
b10 "
b10 :
b11 9
1&
#80000
b11 9
0&
#90000
b0 -
b0 B
b0 +
b0 I
b11 .
b11 A
b11 ,
b11 F
b1 #
b11 :
b100 9
1&
#100000
b100 9
0&
#110000
b11 -
b11 B
b11 +
b11 I
b0 .
b0 A
b0 ,
b0 F
b10 ;
b0 $
b100 :
b100 9
1&
#120000
b10 ;
0&
#130000
0/
1%
b0 -
b0 B
b11 !
b10 <
b0 ;
1&
#140000
1%
b0 ;
0&
#150000
b0 <
0%
b0 ;
1&
