9th+10th Class/Fibo.v
module Fibo 
(
    input wire clk, reset,
    input wire start,
    input wire [4:0] i,
    output reg finish,
    output reg [19:0] result
);

localparam [1:0] idle = 2'b00,
                 op = 2'b01,
                 done = 2'b10,
                 error = 2'b11;

reg [1:0] state_reg, state_next;
reg [19:0] t0_reg, t0_next;
reg [19:0] t1_reg, t1_next;
reg [4:0] n_reg, n_next;


//Memory
always @(posedge clk, posedge reset)
    if(reset)
    begin
        state_reg <= idle;
        t0_reg <= 0;
        t1_reg <= 0;
        n_reg <= 0;
    end
    else
    begin
        state_reg <= state_next;
        t0_reg <= t0_next;
        t1_reg <= t1_next;
        n_reg <= n_next;
    end

//Next State Logic
always@(*)
begin
    $monitor("state_reg = %b\n t0 = %d, t1 = %d, n = %d \n | clk = %b, reset = %b, start = %b, i = %d \n | finish = %b, result = %d\n", state_reg, t0_reg, t1_reg, n_reg, clk, reset, start, i, finish, result);
    
    state_next = state_reg;
    t0_next = t0_reg;
    t1_next = t1_reg;
    n_next = n_reg;

    finish = 'b0;
    result = 'b0;

    case(state_reg)
        idle: 
            if(start)
                begin
                    t0_next = 'b0;
                    t1_next = 'b1;
                    n_next = i;
                    state_next = op;
                end

        op: 
            if(n_reg==0)
            begin
                t1_next = 0;
                state_next = done;
            end
            else if(n_reg == 1)
            begin
                state_next = done;
            end
            else
            begin
                t0_next = t1_reg;
                t1_next = t0_reg + t1_reg;
                n_next = n_reg - 1;
            end
        done: 
            begin
                finish = 'b1;
                result = t1_reg;
            end
        default: state_next = error;
    endcase
end

//output logic
    
endmodule

9th+10th Class/Fibo_tb.v
`timescale 1ns/1ps

module Fibo_tb
();
reg clk;
reg reset;
reg start;
reg [4:0] i;
wire finish;
wire [19:0] result;

Fibo circuit1(
            .clk(clk), 
            .reset(reset), 
            .start(start), 
            .i(i), 
            .finish(finish),
            .result(result)
            );

always begin
    clk = ~clk;
    #10;
end

initial begin
    $dumpfile("test.vcd");
    $dumpvars(0, Fibo_tb);

    clk <= 0;
    reset <= 1;
    start <= 0;
    i <= 0;
    #20;

    reset <= 0;
    start <= 1;
    i <= 5;
    #20;

    #200;

    $finish;
end

// initial begin
//     $monitor("clk = %b, reset = %b, a = %b, b = %b | y0 = %b, y1 = %b\n", clk, reset, a, b, y0, y1);
// end



endmodule

9th+10th Class/test.vcd
$date
	Thu Jun 16 21:55:55 2022
$end
$version
	Icarus Verilog
$end
$timescale
	1ps
$end
$scope module Fibo_tb $end
$var wire 20 ! result [19:0] $end
$var wire 1 " finish $end
$var reg 1 # clk $end
$var reg 5 $ i [4:0] $end
$var reg 1 % reset $end
$var reg 1 & start $end
$scope module circuit1 $end
$var wire 1 # clk $end
$var wire 5 ' i [4:0] $end
$var wire 1 % reset $end
$var wire 1 & start $end
$var reg 1 " finish $end
$var reg 5 ( n_next [4:0] $end
$var reg 5 ) n_reg [4:0] $end
$var reg 20 * result [19:0] $end
$var reg 2 + state_next [1:0] $end
$var reg 2 , state_reg [1:0] $end
$var reg 20 - t0_next [19:0] $end
$var reg 20 . t0_reg [19:0] $end
$var reg 20 / t1_next [19:0] $end
$var reg 20 0 t1_reg [19:0] $end
$upscope $end
$upscope $end
$enddefinitions $end
#0
$dumpvars
b0 0
b0 /
b0 .
b0 -
b0 ,
b0 +
b0 *
b0 )
b0 (
b0 '
0&
1%
b0 $
0#
0"
b0 !
$end
#10000
1#
#20000
b1 +
b101 (
b1 /
b101 $
b101 '
1&
0%
0#
#30000
b1 -
b101 )
b1 0
b1 ,
b100 (
b1 /
b1 +
1#
#40000
b100 (
b1 -
0#
#50000
b10 /
b100 )
b1 .
b11 (
b1 -
1#
#60000
b11 (
b10 /
0#
#70000
b10 -
b11 )
b10 0
b10 (
b11 /
1#
#80000
b10 (
b11 /
b10 -
0#
#90000
b10 )
b11 0
b10 .
b1 (
b101 /
b11 -
1#
#100000
b1 (
b101 /
b11 -
0#
#110000
b10 +
b1 )
b101 0
b11 .
b1 (
b101 /
b11 -
1#
#120000
b10 +
0#
#130000
b101 !
b101 *
1"
b10 ,
b10 +
1#
#140000
b101 !
b101 *
1"
0#
#150000
b101 !
b101 *
1"
1#
#160000
b101 !
b101 *
1"
0#
#170000
b101 !
b101 *
1"
1#
#180000
b101 !
b101 *
1"
0#
#190000
b101 !
b101 *
1"
1#
#200000
b101 !
b101 *
1"
0#
#210000
b101 !
b101 *
1"
1#
#220000
b101 !
b101 *
1"
0#
#230000
b101 !
b101 *
1"
1#
